README.rst
setup.cfg
setup.py
calibtools/__init__.py
calibtools/calib.py
calibtools/tool.py
calibtools/undistort.py
calibtools/util.py
calibtools.egg-info/PKG-INFO
calibtools.egg-info/SOURCES.txt
calibtools.egg-info/dependency_links.txt
calibtools.egg-info/entry_points.txt
calibtools.egg-info/requires.txt
calibtools.egg-info/top_level.txt