Metadata-Version: 1.1
Name: calibtools
Version: 0.3.0
Summary: Camera calibration tools for Python
Home-page: https://github.com/rjw57/calibtools/
Author: Rich Wareham
Author-email: rich.calibtools@richwareham.com
License: MIT
Platform: UNKNOWN
Classifier: Development Status :: 3 - Alpha
Classifier: Environment :: Console
Classifier: Intended Audience :: Science/Research
Classifier: Intended Audience :: Developers
Classifier: License :: OSI Approved :: MIT License
Classifier: Natural Language :: English
Classifier: Operating System :: POSIX
Classifier: Programming Language :: Python :: 3
Classifier: Topic :: Scientific/Engineering
Classifier: Topic :: Utilities
